proxyUtil/__init__.py
proxyUtil/__version__.py
proxyUtil/cdnGen.py
proxyUtil/cfRecorder.py
proxyUtil/dnsChecker.py
proxyUtil/dnsUrl.py
proxyUtil/dnsUtil.py
proxyUtil/ipExtractor.py
proxyUtil/logFormatter.py
proxyUtil/myUtil.py
proxyUtil/v2rayChecker.py
proxyUtil/data/Clash-Template.yaml
proxyUtil-0.1.3.data/scripts/clashGen
proxyUtil-0.1.3.data/scripts/connectMe
proxyUtil-0.1.3.data/scripts/shadowChecker
proxyUtil-0.1.3.data/scripts/ssURI2sslocal
proxyUtil-0.1.3.data/scripts/sslocal2ssURI
proxyUtil-0.1.3.dist-info/LICENSE
proxyUtil-0.1.3.dist-info/METADATA
proxyUtil-0.1.3.dist-info/WHEEL
proxyUtil-0.1.3.dist-info/entry_points.txt
proxyUtil-0.1.3.dist-info/top_level.txt
proxyUtil-0.1.3.dist-info/RECORD
