Metadata-Version: 2.1
Name: proxyUtil
Version: 0.1.3
Summary: some proxy tools
Home-page: https://github.com/mheidari98/proxyUtil
Author: Mahdi Heidari
Author-email: mahdih3idari@gmail.com
License: MIT License
Classifier: Development Status :: 3 - Alpha
Classifier: Intended Audience :: Developers
Classifier: License :: OSI Approved :: MIT License
Classifier: Operating System :: POSIX :: Linux
Classifier: Programming Language :: Python :: 3
Requires-Python: >=3
License-File: LICENSE
Requires-Dist: anyio (==3.6.2)
Requires-Dist: attrs (==22.2.0)
Requires-Dist: beautifulsoup4 (==4.11.1)
Requires-Dist: certifi (==2022.12.7)
Requires-Dist: cffi (==1.15.1)
Requires-Dist: charset-normalizer (==2.1.1)
Requires-Dist: cloudflare (==2.11.1)
Requires-Dist: cryptography (==39.0.1)
Requires-Dist: dnspython (==2.3.0)
Requires-Dist: h11 (==0.14.0)
Requires-Dist: h2 (==4.1.0)
Requires-Dist: hpack (==4.0.0)
Requires-Dist: httpcore (==0.16.3)
Requires-Dist: httpx (==0.23.3)
Requires-Dist: hyperframe (==6.0.1)
Requires-Dist: idna (==3.4)
Requires-Dist: jsonlines (==3.1.0)
Requires-Dist: markdown-it-py (==2.2.0)
Requires-Dist: mdurl (==0.1.2)
Requires-Dist: numpy (==1.23.4)
Requires-Dist: psutil (==5.9.2)
Requires-Dist: pycparser (==2.21)
Requires-Dist: Pygments (==2.14.0)
Requires-Dist: PySocks (==1.7.1)
Requires-Dist: PyYAML (==6.0)
Requires-Dist: requests (==2.28.1)
Requires-Dist: requests-toolbelt (==0.10.1)
Requires-Dist: rfc3986 (==1.5.0)
Requires-Dist: rich (==13.3.1)
Requires-Dist: ruamel.yaml (==0.17.21)
Requires-Dist: ruamel.yaml.clib (==0.2.7)
Requires-Dist: sniffio (==1.3.0)
Requires-Dist: soupsieve (==2.3.2.post1)
Requires-Dist: urllib3 (==1.26.12)
Provides-Extra: dev
Requires-Dist: pytest (>=3.7) ; extra == 'dev'
Requires-Dist: twine ; extra == 'dev'
